{
    "Version": "2012-10-17",
    "Statement": [
        {
            "Sid": "VisualEditor0",
            "Effect": "Allow",
            "Action": [
                "ec2:DescribeCapacityReservations",
                "ec2:DescribeInstances",
                "sns:DeleteTopic",
                "cloudwatch:DeleteAlarms",
                "ec2:DescribeRegions",
                "sns:CreateTopic",
                "sns:ListTopics",
                "sns:SetTopicAttributes",
                "ec2:DescribeImages",
                "cloudwatch:PutMetricAlarm",
                "ec2:ModifyCapacityReservation",
                "ec2:CreateCapacityReservation",
                "ec2:CancelCapacityReservation",
                "ec2:DescribeReservedInstances",
                "ec2:DescribeInstanceStatus"
            ],
            "Resource": "*"
        },
        {
            "Sid": "VisualEditor1",
            "Effect": "Allow",
            "Action": [
                "sns:Publish",
                "sns:Subscribe"
            ],
            "Resource": "arn:aws:sns:*:*:ODCRAlarmNotificationTopic"
        }
    ]
}
